fcontin/ContProblem.py
fcontin/__init__.py
FContin-0.1.dist-info/LICENSE.txt
FContin-0.1.dist-info/METADATA
FContin-0.1.dist-info/WHEEL
FContin-0.1.dist-info/top_level.txt
FContin-0.1.dist-info/RECORD
