Metadata-Version: 2.1
Name: FContin
Version: 0.1
Summary: Numerical continuation using just the function
Home-page: https://github.com/gpavanb1/FContin
Author: gpavanb1
Author-email: gpavanb@gmail.com
License: MIT
Project-URL: Bug Reports, https://github.com/gpavanb1/FContin/issues
Project-URL: Source, https://github.com/gpavanb1/FContin/
Keywords: arclength python continuation numerical
Platform: UNKNOWN
Classifier: Topic :: Scientific/Engineering :: Mathematics
Classifier: License :: OSI Approved :: MIT License
Classifier: Programming Language :: Python :: 3
Classifier: Programming Language :: Python :: 3.6
Classifier: Programming Language :: Python :: 3.7
Classifier: Programming Language :: Python :: 3 :: Only
Requires-Dist: numpy
Requires-Dist: scipy
Requires-Dist: jax
Requires-Dist: jaxlib
Requires-Dist: numdifftools
Requires-Dist: pacopy
